depkit/__init__.py
depkit/depmanager.py
depkit/exceptions.py
depkit/log.py
depkit/parser.py
depkit/py.typed
depkit/utils.py
depkit-1.0.3.dist-info/licenses/LICENSE
depkit-1.0.3.dist-info/WHEEL
depkit-1.0.3.dist-info/METADATA
depkit-1.0.3.dist-info/RECORD
