Metadata-Version: 2.4
Name: depkit
Version: 1.0.3
Summary: Tools to manage (uv) environemnts programmatically.
Keywords: 
Author: Philipp Temminghoff
Author-email: Philipp Temminghoff <philipptemminghoff@googlemail.com>
License-Expression: MIT
License-File: LICENSE
Classifier: Development Status :: 4 - Beta
Classifier: Intended Audience :: Developers
Classifier: Operating System :: OS Independent
Classifier: Programming Language :: Python :: 3
Classifier: Programming Language :: Python :: 3 :: Only
Classifier: Programming Language :: Python :: 3.12
Classifier: Programming Language :: Python :: 3.13
Classifier: Programming Language :: Python :: 3.14
Classifier: Topic :: Documentation
Classifier: Topic :: Software Development
Classifier: Topic :: Utilities
Classifier: Typing :: Typed
Requires-Dist: packaging>=25.0
Requires-Dist: upathtools>=0.6.5
Requires-Python: >=3.13
Project-URL: Code coverage, https://app.codecov.io/gh/phil65/depkit
Project-URL: Discussions, https://github.com/phil65/depkit/discussions
Project-URL: Documentation, https://phil65.github.io/depkit/
Project-URL: Issues, https://github.com/phil65/depkit/issues
Project-URL: Source, https://github.com/phil65/depkit
